{
  "occurrence": {
    "type": "rule_based",
    "metrics": {
      "count_exact_acc": 12.7551,
      "count_mae": 5.051,
      "weekly_total_mae": 10.4898,
      "presence_f1": 97.5822
    }
  },
  "temporal": {
    "metrics": {
      "start_exact_acc": 9.8014,
      "start_tol_acc_5m": 9.8991,
      "start_tol_acc_10m": 10.6806,
      "start_mae_minutes": 1131.6184,
      "duration_mae_minutes": 1.0805
    },
    "meta": {
      "best_epoch": 1,
      "monitor_name": "e2e_joint_score",
      "monitor_value": -781.9326
    }
  },
  "ensemble": {
    "metrics": {
      "task_precision": 84.44,
      "task_recall": 83.07,
      "task_f1": 83.75,
      "time_exact_accuracy": 0.0,
      "time_close_accuracy_5m": 0.0,
      "time_close_accuracy_10m": 0.0,
      "duration_close_accuracy": 0.0,
      "start_mae_minutes": 0.0,
      "overlap_same_device_count": 173.0
    }
  },
  "per_task_final": {
    "Assist": {
      "total": 383.0,
      "task_accuracy": 0.0,
      "time_exact_accuracy": 0.0
    },
    "Clean": {
      "total": 804.0,
      "task_accuracy": 0.0,
      "time_exact_accuracy": 0.0
    },
    "Delivery": {
      "total": 431.0,
      "task_accuracy": 0.0,
      "time_exact_accuracy": 0.0
    },
    "Patroll": {
      "total": 933.0,
      "task_accuracy": 0.0,
      "time_exact_accuracy": 0.0
    }
  },
  "meta": {
    "occurrence_model_kind": "structured_lag4",
    "prediction_use_repair": true,
    "best_epoch_temporal": 1,
    "monitor_name": "e2e_joint_score",
    "monitor_value": -781.9326
  },
  "report_path": "/home/miguel/Escritorio/prediction_deliverance/project_06_v3/reports/training_report.json"
}